html_classes/__init__.py
html_classes/basic.py
html_classes/bs4.py
html_classes/font_awesome.py
html_classes/html.py
make_html-0.0.2.dist-info/METADATA
make_html-0.0.2.dist-info/WHEEL
make_html-0.0.2.dist-info/top_level.txt
make_html-0.0.2.dist-info/RECORD
