Metadata-Version: 2.1
Name: make-html
Version: 0.0.2
Summary: Classes to generate HTML
Author: Ian Jones
Project-URL: Homepage, https://github.com/jonesim/html-classes
Classifier: License :: OSI Approved :: MIT License
Classifier: Programming Language :: Python
Classifier: Programming Language :: Python :: 3
Requires-Python: >=3.9
